scrapy_middlewares/__init__.py
scrapy_middlewares/req_async_middleware.py
scrapy_middlewares/req_middleware.py
scrapy_middlewares/req_settings.py
scrapy_middlewares/req_sync_middleware.py
scrapy_middlewares/scrapy_requests.py
scrapy_middlewares-1.0.2.dist-info/LICENSE
scrapy_middlewares-1.0.2.dist-info/METADATA
scrapy_middlewares-1.0.2.dist-info/WHEEL
scrapy_middlewares-1.0.2.dist-info/top_level.txt
scrapy_middlewares-1.0.2.dist-info/RECORD
