Metadata-Version: 2.1
Name: scrapy-middlewares
Version: 1.0.2
Summary: scrapy middleware
Home-page: https://github.com/CLannadZSY/scrapy-middlewares
Author: CLannadZSY
Author-email: zsymidi@gmail.com
License: UNKNOWN
Platform: UNKNOWN
Classifier: Programming Language :: Python :: 3
Classifier: License :: OSI Approved :: MIT License
Classifier: Operating System :: OS Independent
Requires-Python: >=3.0
